xlhelper/__init__.py
xlhelper-0.1.0.dist-info/DESCRIPTION.rst
xlhelper-0.1.0.dist-info/METADATA
xlhelper-0.1.0.dist-info/RECORD
xlhelper-0.1.0.dist-info/WHEEL
xlhelper-0.1.0.dist-info/metadata.json
xlhelper-0.1.0.dist-info/top_level.txt
