Metadata-Version: 2.0
Name: xlhelper
Version: 0.1.0
Summary: Some small minimal helper functions for loading Excel
Home-page: https://github.com/darth-veitcher/xlhelper
Author: James Veitch
Author-email: james@jamesveitch.com
License: MIT
Platform: UNKNOWN
Requires-Python: >=3, <4
Requires-Dist: openpyxl
